{
    "created_time": "2018-07-18T06:05:34Z",
    "files": [
        {
            "attachment_folder": "",
            "attachments": [
            ],
            "created_time": "2018-07-18T06:13:20Z",
            "modified_time": "2018-12-27T10:16:07Z",
            "name": "Servlet之简介.md",
            "tags": [
            ]
        },
        {
            "attachment_folder": "",
            "attachments": [
            ],
            "created_time": "2018-12-27T10:40:12Z",
            "modified_time": "2018-12-28T03:33:56Z",
            "name": "Servlet之域对象.md",
            "tags": [
            ]
        },
        {
            "attachment_folder": "",
            "attachments": [
            ],
            "created_time": "2018-12-27T10:15:01Z",
            "modified_time": "2018-12-28T02:53:13Z",
            "name": "Servlet之ServletContext.md",
            "tags": [
            ]
        },
        {
            "attachment_folder": "",
            "attachments": [
            ],
            "created_time": "2018-12-28T02:57:59Z",
            "modified_time": "2018-12-28T03:31:20Z",
            "name": "Servlet之Session.md",
            "tags": [
            ]
        },
        {
            "attachment_folder": "",
            "attachments": [
            ],
            "created_time": "2018-12-28T03:34:13Z",
            "modified_time": "2018-12-28T03:45:08Z",
            "name": "Servlet之HttpServletRequest.md",
            "tags": [
            ]
        }
    ],
    "sub_directories": [
    ],
    "version": "1"
}
